{
  "Title": "朝日杯FSにむけて",
  "TextBlockList": [
    {
      "Name": "",
      "Text": "",
      "ChoiceDataList": [],
      "ColorTextInfoList": []
    },
    {
      "Name": "",
      "Text": "『朝日杯FS』当日。ヤエノムテキは、\r\n自分の好敵手になるかもしれないと\nサクラチヨノオーの観戦に来ていた。",
      "ChoiceDataList": [],
      "ColorTextInfoList": []
    },
    {
      "Name": "",
      "Text": "好敵手を見つけ、己を磨き成長することこそ、\r\n1度道を踏み外しかけた自分を救ってくれた\n祖父への恩返しだと思っていたのだ。",
      "ChoiceDataList": [],
      "ColorTextInfoList": []
    },
    {
      "Name": "",
      "Text": "一方、メジロアルダンはドクターストップが\r\nかかり、見学にすら来られなかったらしい。\n……彼女の体は余程繊細なもののようだ。",
      "ChoiceDataList": [],
      "ColorTextInfoList": []
    },
    {
      "Name": "",
      "Text": "サクラチヨノオーはマルゼンスキーが\r\n過去に優勝した朝日杯FSで走れることを\n噛みしめ、パドックへと向かうのだった。",
      "ChoiceDataList": [],
      "ColorTextInfoList": []
    }
  ]
}