{
  "Title": "日本德比之後・宿命的孤星",
  "TextBlockList": [
    {
      "Name": "",
      "Text": "",
      "ChoiceDataList": [],
      "ColorTextInfoList": []
    },
    {
      "Name": "獨白",
      "Text": "勝敗は決した。アドマイヤベガは1著だった。\r\nウイナーズ・サークルで彼女は、\n湧き上がる熱と喜びをかみしめていた……。",
      "ChoiceDataList": [],
      "ColorTextInfoList": []
    },
    {
      "Name": "獨白",
      "Text": "次はクラシック三冠路線の最終戦、菊花賞で。\r\nライバルともそう誓いあって──",
      "ChoiceDataList": [],
      "ColorTextInfoList": [
        "菊花賞"
      ]
    },
    {
      "Name": "獨白",
      "Text": "楽しさを胸に、夏が來ようとしていた。",
      "ChoiceDataList": [],
      "ColorTextInfoList": []
    }
  ]
}