{
  "Title": "夏天開始了",
  "TextBlockList": [
    {
      "Name": "",
      "Text": "",
      "ChoiceDataList": [],
      "ColorTextInfoList": []
    },
    {
      "Name": "サイレンススズカ",
      "Text": "（初夏が過ぎて、セミが鳴き、朝の風がもっと暖かくなった頃。\n――私たちの夏合宿は、そんな空気のさなかに、始まる）",
      "ChoiceDataList": [],
      "ColorTextInfoList": []
    },
    {
      "Name": "アグネスタキオン",
      "Text": "いやぁ～、始まるねぇ！\n楽しい楽しい、夏合宿が！",
      "ChoiceDataList": [],
      "ColorTextInfoList": []
    },
    {
      "Name": "ジャングルポケット",
      "Text": "はーん？\u3000なんか企んでんなぁ、タキオン。",
      "ChoiceDataList": [],
      "ColorTextInfoList": []
    },
    {
      "Name": "アグネスタキオン",
      "Text": "ははは、穿った推測はよしたまえ。私は一生徒として、\n夏合宿を満喫し、心身の成長を促せたらと考えているだけさ。",
      "ChoiceDataList": [],
      "ColorTextInfoList": []
    },
    {
      "Name": "ジャングルポケット",
      "Text": "嘘つけ！\u3000『学園でトレーニングしたほうが効率的じゃないか』\nって、この間までブツブツ言ってたじゃねぇか！",
      "ChoiceDataList": [],
      "ColorTextInfoList": []
    },
    {
      "Name": "アグネスタキオン",
      "Text": "空耳だろうね。",
      "ChoiceDataList": [],
      "ColorTextInfoList": []
    },
    {
      "Name": "マンハッタンカフェ",
      "Text": "『長期的な集団宿泊活動によるウマ娘の心身の変化』\nについての研究ですよ……。",
      "ChoiceDataList": [],
      "ColorTextInfoList": []
    },
    {
      "Name": "ジャングルポケット",
      "Text": "ちょうき……は？",
      "ChoiceDataList": [],
      "ColorTextInfoList": []
    },
    {
      "Name": "マンハッタンカフェ",
      "Text": "『本学園において夏合宿とは、特別なトレーニング及び一般的な\n長期的集団宿泊活動と同様の教育効果を期待される行事である』",
      "ChoiceDataList": [],
      "ColorTextInfoList": []
    },
    {
      "Name": "マンハッタンカフェ",
      "Text": "『その中でウマ娘が実際にどの程度精神的な成長を見せるか、\nこれらがもたらす身体への影響について、緻密なデータを今夏――』",
      "ChoiceDataList": [],
      "ColorTextInfoList": []
    },
    {
      "Name": "アグネスタキオン",
      "Text": "カーフェ！\u3000やめろやめろなんだい君は！\u3000台無しにする気かい！\nというかそもそもいったいどこでこの機密書類を――",
      "ChoiceDataList": [],
      "ColorTextInfoList": []
    },
    {
      "Name": "マンハッタンカフェ",
      "Text": "私とアナタの、共有スペースの床ですが……。\n……そうですか、機密書類でしたか。",
      "ChoiceDataList": [],
      "ColorTextInfoList": []
    },
    {
      "Name": "ジャングルポケット",
      "Text": "ほーらやっぱり！\u3000妙なこと企んでたじゃねーの！",
      "ChoiceDataList": [],
      "ColorTextInfoList": []
    },
    {
      "Name": "アグネスタキオン",
      "Text": "待て待て、妙なこと――かどうかは君らの主観にゆだねるが、\n要するにあくまで私は真面目に夏合宿を楽しむだけだ！",
      "ChoiceDataList": [],
      "ColorTextInfoList": []
    },
    {
      "Name": "アグネスタキオン",
      "Text": "君らが顔をしかめるような、発光や毛色の変化の予定はない！\nいいかい、あくまで行動は模範的。……少々データを頂くだけさ。",
      "ChoiceDataList": [],
      "ColorTextInfoList": []
    },
    {
      "Name": "カフェ＆ポッケ",
      "Text": "…………。\n……へぇ……。",
      "ChoiceDataList": [],
      "ColorTextInfoList": []
    },
    {
      "Name": "エアグルーヴ",
      "Text": "まったく、合宿だというのに遠足気分だな……。\n合宿所でも騒ぎすぎなければいいが。",
      "ChoiceDataList": [],
      "ColorTextInfoList": []
    },
    {
      "Name": "サイレンススズカ",
      "Text": "…………。",
      "ChoiceDataList": [],
      "ColorTextInfoList": []
    },
    {
      "Name": "",
      "Text": "イベントタイトル。",
      "ChoiceDataList": [],
      "ColorTextInfoList": []
    },
    {
      "Name": "先生A",
      "Text": "はーい、全員到着しましたね。これからは基本的に集団生活と\nなります。普段以上にみんなで協力し合うことを意識しましょう！",
      "ChoiceDataList": [],
      "ColorTextInfoList": []
    },
    {
      "Name": "先生A",
      "Text": "トレーナーがいる子たちはトレーナーの指示に従ってね。\nというわけで、いったん解散！",
      "ChoiceDataList": [],
      "ColorTextInfoList": []
    },
    {
      "Name": "エアグルーヴ",
      "Text": "207号室のリーダーは私――エアグルーヴだ。\nよろしく頼む。さあ、まずは部屋へ移動しよう。",
      "ChoiceDataList": [],
      "ColorTextInfoList": []
    },
    {
      "Name": "207号室のウマ娘達",
      "Text": "はい。\nはーい！",
      "ChoiceDataList": [],
      "ColorTextInfoList": []
    },
    {
      "Name": "エアグルーヴ",
      "Text": "……おい、聞いているかタキオン、ポッケ！\nお前たちも207号室だぞ。",
      "ChoiceDataList": [],
      "ColorTextInfoList": []
    },
    {
      "Name": "タキオン＆ポッケ",
      "Text": "ん？\u3000はいはい聞いてるよ。\nあ？\u3000聞いてる聞いてる。",
      "ChoiceDataList": [],
      "ColorTextInfoList": []
    },
    {
      "Name": "アグネスタキオン",
      "Text": "ほう、ここが今日から我々が共に過ごす空間か。\nまぁ悪くないな。まずは隅々まで調査、と……。",
      "ChoiceDataList": [],
      "ColorTextInfoList": []
    },
    {
      "Name": "アグネスタキオン",
      "Text": "見晴らしは……悪くない。\n押入れは布団の山で――あれはないのかい、菓子盆は！",
      "ChoiceDataList": [],
      "ColorTextInfoList": []
    },
    {
      "Name": "ジャングルポケット",
      "Text": "バーカ、旅館じゃねーんだぞ。\n……うわっ、冷蔵庫ある！\u3000コーラ入れようぜ！\u3000コーラ！",
      "ChoiceDataList": [],
      "ColorTextInfoList": []
    },
    {
      "Name": "エアグルーヴ",
      "Text": "ほら、皆荷物は部屋の隅にまとめておけ。\n初日と言えど忙しいからな、さっさとジャージに着替えるぞ。",
      "ChoiceDataList": [],
      "ColorTextInfoList": []
    },
    {
      "Name": "サイレンススズカ",
      "Text": "…………。",
      "ChoiceDataList": [],
      "ColorTextInfoList": []
    },
    {
      "Name": "サイレンススズカ",
      "Text": "（こうして、夏合宿は幕を開けたのだけれど――）",
      "ChoiceDataList": [],
      "ColorTextInfoList": []
    },
    {
      "Name": "元気なウマ娘",
      "Text": "うはーっ！\u3000広い！\u3000青い！\u3000走ってて楽っしー！！",
      "ChoiceDataList": [],
      "ColorTextInfoList": []
    },
    {
      "Name": "明るいウマ娘",
      "Text": "教官教官～！\nここでのトレーニングなら私、めちゃめちゃタイム縮みそうですー！",
      "ChoiceDataList": [],
      "ColorTextInfoList": []
    },
    {
      "Name": "食いしん坊のウマ娘",
      "Text": "ああ～、去年の最終日にあったBBQ大会楽しかったな～！\n山盛りのにんじん、フルーツ、たーっぷり食べ放題で！",
      "ChoiceDataList": [],
      "ColorTextInfoList": []
    },
    {
      "Name": "ヤンキーなウマ娘",
      "Text": "そーいや、BBQ後にやったビンゴでハンディファン\n当てたんだけど、そーとーよくってさぁ。一生使ってるわ。",
      "ChoiceDataList": [],
      "ColorTextInfoList": []
    },
    {
      "Name": "清楚なウマ娘",
      "Text": "ふー……！\u3000やっぱり慣れない場所だと緊張してしまって\nいたのか……。ふふ、1日の疲れが癒されますね。",
      "ChoiceDataList": [],
      "ColorTextInfoList": []
    },
    {
      "Name": "朗らかなウマ娘",
      "Text": "うん、この後の食事も楽しみ……と、そういえば\n配膳当番だったような！\u3000ごめん、私そろそろ上がるね。",
      "ChoiceDataList": [],
      "ColorTextInfoList": []
    },
    {
      "Name": "ウマ娘たち",
      "Text": "――いただきます！",
      "ChoiceDataList": [],
      "ColorTextInfoList": []
    },
    {
      "Name": "ジャングルポケット",
      "Text": "――はぁ！？\u3000タキオンがBBQ実行委員長！？\nお前……っ、そこまでやるのか！",
      "ChoiceDataList": [],
      "ColorTextInfoList": []
    },
    {
      "Name": "アグネスタキオン",
      "Text": "ハッハッハッハ！\u3000当然！\n誰より夏合宿を楽しむのが今年のアグネスタキオンさ！",
      "ChoiceDataList": [],
      "ColorTextInfoList": []
    },
    {
      "Name": "アグネスタキオン",
      "Text": "何よりBBQ大会は、全生徒の一大イベント。刺激的な日であれば\nあるほど、皆の報酬系への刺激は強まる。ならば舞台を整えねばね！",
      "ChoiceDataList": [],
      "ColorTextInfoList": []
    },
    {
      "Name": "マンハッタンカフェ",
      "Text": "合宿には、トレーニングのために来ているんです……。\nそっちにも……やる気を見せたほうが、いいですよ……。",
      "ChoiceDataList": [],
      "ColorTextInfoList": []
    },
    {
      "Name": "アグネスタキオン",
      "Text": "なんとも『真っ当』なことを言うね、君も。\n……まぁそれも一理あるか、私も今回のモルモットの1人だ。",
      "ChoiceDataList": [],
      "ColorTextInfoList": []
    },
    {
      "Name": "アグネスタキオン",
      "Text": "――ともかく、しばらくは同じ屋根の下で、同じ釜の飯を\n食らう仲。この特異な状況を満喫しようじゃないか！",
      "ChoiceDataList": [],
      "ColorTextInfoList": []
    },
    {
      "Name": "サイレンススズカ",
      "Text": "…………。",
      "ChoiceDataList": [],
      "ColorTextInfoList": []
    }
  ]
}