{
  "Title": "在眾多的視線之外",
  "TextBlockList": [
    {
      "Name": "",
      "Text": "",
      "ChoiceDataList": [],
      "ColorTextInfoList": []
    },
    {
      "Name": "電視傳來的聲音",
      "Text": "「這裡就是眾多馬娘的夢想，閃耀系列賽！\n究竟誰能站上頂點，刻下自己的名字呢──！」",
      "ChoiceDataList": [],
      "ColorTextInfoList": []
    },
    {
      "Name": "葛城王牌",
      "Text": "那座舞台，是遙遠又令人憧憬的場所。",
      "ChoiceDataList": [],
      "ColorTextInfoList": []
    },
    {
      "Name": "悠哉的小孩子們",
      "Text": "好厲害好厲害！那個馬娘好快喔！\n咻咻──地就像風一樣！",
      "ChoiceDataList": [],
      "ColorTextInfoList": []
    },
    {
      "Name": "大方外向的男性",
      "Text": "果然閃耀系列賽播起來魄力就是不一樣啊！\n欸，喂攝影機！再拍前面一點啦。",
      "ChoiceDataList": [],
      "ColorTextInfoList": []
    },
    {
      "Name": "葛城王牌",
      "Text": "在沒什麼娛樂的鄉下小鎮觀賞的電視，\n其內容既繽紛又華麗，每個人都說那是「另一個世界」。",
      "ChoiceDataList": [],
      "ColorTextInfoList": []
    },
    {
      "Name": "葛城王牌",
      "Text": "但話不是這麼說的吧？",
      "ChoiceDataList": [],
      "ColorTextInfoList": []
    },
    {
      "Name": "葛城王牌",
      "Text": "那個場所，和這裡的天空相連著。\n只是現在還離得很遠。",
      "ChoiceDataList": [],
      "ColorTextInfoList": []
    },
    {
      "Name": "葛城王牌",
      "Text": "所以，我──！",
      "ChoiceDataList": [],
      "ColorTextInfoList": []
    },
    {
      "Name": "等待招募的馬娘",
      "Text": "我的夢想嗎？那當然是贏下比賽囉！\n我認為只要是馬娘大家都一樣。",
      "ChoiceDataList": [
        "那樣的話──"
      ],
      "ColorTextInfoList": []
    },
    {
      "Name": "獨白",
      "Text": "我試著問她，要不要一起以頂點為目標。",
      "ChoiceDataList": [],
      "ColorTextInfoList": []
    },
    {
      "Name": "獨白",
      "Text": "我自己的夢想，就是讓擔當的馬娘拿下許多G1，\n並且施予能讓他們打敗世界各地知名馬娘的指導──",
      "ChoiceDataList": [
        "我要成為那樣的訓練員。"
      ],
      "ColorTextInfoList": []
    },
    {
      "Name": "等待招募的馬娘",
      "Text": "說得也是。當訓練員的也會做那種夢呢。\n好高騖遠的夢想也是自由嘛。彼此互相加油吧！掰！",
      "ChoiceDataList": [],
      "ColorTextInfoList": []
    },
    {
      "Name": "獨白",
      "Text": "……我本來是要進行招募的。但是我的話似乎沒有被認真看待。",
      "ChoiceDataList": [
        "……好高騖遠的夢想啊。"
      ],
      "ColorTextInfoList": []
    },
    {
      "Name": "獨白",
      "Text": "新人訓練員高呼遠大的夢想。\n不管多麼認真，在旁人眼中都只是有勇無謀嗎？",
      "ChoiceDataList": [],
      "ColorTextInfoList": []
    },
    {
      "Name": "葛城王牌",
      "Text": "哈啊啊啊啊啊啊！！",
      "ChoiceDataList": [],
      "ColorTextInfoList": []
    },
    {
      "Name": "葛城王牌",
      "Text": "哈、哈啊、哈啊……哈啊……。",
      "ChoiceDataList": [],
      "ColorTextInfoList": []
    },
    {
      "Name": "葛城王牌",
      "Text": "……呿，剛才跑得不怎麼樣啊……。\n哈……最後，是不是腳步踩得不夠扎實啊？……哼！",
      "ChoiceDataList": [],
      "ColorTextInfoList": []
    },
    {
      "Name": "獨白",
      "Text": "不知道她跑了多久。臉上早已滑落了大量的汗水。",
      "ChoiceDataList": [
        "好厲害……"
      ],
      "ColorTextInfoList": []
    },
    {
      "Name": "獨白",
      "Text": "她沒有展現特別突出的速度，也沒有和他人截然不同的強悍。",
      "ChoiceDataList": [],
      "ColorTextInfoList": []
    },
    {
      "Name": "獨白",
      "Text": "就像是單純把無法克制的力量全部傾洩出來般激情的奔馳──",
      "ChoiceDataList": [],
      "ColorTextInfoList": []
    },
    {
      "Name": "獨白",
      "Text": "但這是怎麼回事。我無法移開視線。\n她的眼神就像是在追尋某種看不見的東西，蘊藏無法克制的熱情──",
      "ChoiceDataList": [],
      "ColorTextInfoList": []
    },
    {
      "Name": "葛城王牌",
      "Text": "哈──……！好，再多跑幾趟吧。讓大家見識到我不是這種程──",
      "ChoiceDataList": [],
      "ColorTextInfoList": []
    },
    {
      "Name": "老手訓練員A",
      "Text": "那什麼跑法啊……！抱歉，能不能稍微聊一下！？",
      "ChoiceDataList": [],
      "ColorTextInfoList": []
    },
    {
      "Name": "看似緊張的馬娘",
      "Text": "好、好帥喔～……！這感覺才是所謂真正的奔馳……\n那個，我也想聊……。",
      "ChoiceDataList": [],
      "ColorTextInfoList": []
    },
    {
      "Name": "獨白",
      "Text": "我注意到喧嚷聲而移動視線。\n發現那裡聚集了許多的訓練員和馬娘們，還有──",
      "ChoiceDataList": [],
      "ColorTextInfoList": []
    },
    {
      "Name": "千明代表",
      "Text": "……呼，抱歉啊。我還沒跑夠。\n很抱歉，下次再說吧。再見。",
      "ChoiceDataList": [],
      "ColorTextInfoList": []
    },
    {
      "Name": "獨白",
      "Text": "那位馬娘毫不在乎周遭的人群，走向了賽道。從關注度來看，想必是非常有名的馬娘吧。",
      "ChoiceDataList": [],
      "ColorTextInfoList": []
    },
    {
      "Name": "獨白",
      "Text": "但是我──很快地將視線移回剛才的馬娘。\n不過人已經不在那裡了……。",
      "ChoiceDataList": [],
      "ColorTextInfoList": []
    },
    {
      "Name": "千明代表",
      "Text": "哈、哈、哈……！",
      "ChoiceDataList": [],
      "ColorTextInfoList": []
    },
    {
      "Name": "千明代表",
      "Text": "……哈哈！從剛才開始就感受到的強烈視線是……。",
      "ChoiceDataList": [],
      "ColorTextInfoList": []
    },
    {
      "Name": "葛城王牌",
      "Text": "衝啊啊啊啊！！",
      "ChoiceDataList": [],
      "ColorTextInfoList": []
    },
    {
      "Name": "千明代表",
      "Text": "原來是妳啊？葛城王牌。",
      "ChoiceDataList": [],
      "ColorTextInfoList": []
    },
    {
      "Name": "葛城王牌",
      "Text": "唷，千明……！妳好像挺無聊的呢？\n哈……不然就由我來陪妳吧！？",
      "ChoiceDataList": [],
      "ColorTextInfoList": []
    },
    {
      "Name": "千明代表",
      "Text": "難道這是併跑的邀請嗎？\n我本來想說，最後簡單跑個幾圈之後就要去散步了──",
      "ChoiceDataList": [],
      "ColorTextInfoList": []
    },
    {
      "Name": "葛城王牌",
      "Text": "哈……嘿嘿，妳會答應吧？",
      "ChoiceDataList": [],
      "ColorTextInfoList": []
    },
    {
      "Name": "千明代表",
      "Text": "……好啊，那就玩一下吧！",
      "ChoiceDataList": [],
      "ColorTextInfoList": []
    },
    {
      "Name": "獨白",
      "Text": "我移動到能看清楚兩人身影的地方，默默看著他們奔馳。\n伴隨著越來越大的喧嚷，兩人的跑法也隨著改變。",
      "ChoiceDataList": [],
      "ColorTextInfoList": []
    },
    {
      "Name": "老手訓練員A",
      "Text": "喔喔，氣魄真是驚人……！\n逐漸把和對手間的距離拉開了！",
      "ChoiceDataList": [],
      "ColorTextInfoList": []
    },
    {
      "Name": "看似緊張的馬娘",
      "Text": "好厲害……千明學姊像是乘風破浪的奔馳……。\n葛城王牌學姊根本追不上！",
      "ChoiceDataList": [],
      "ColorTextInfoList": []
    },
    {
      "Name": "獨白",
      "Text": "那是一場宛如正式比賽般的奔馳。\n但是受到大家注目的，卻只有一位馬娘──",
      "ChoiceDataList": [],
      "ColorTextInfoList": []
    },
    {
      "Name": "老手訓練員A",
      "Text": "跑得真是太優秀了！千明代表，請讓我為妳做指導吧！\n我一定能幫妳鋪出邁向勝利的康莊大道！",
      "ChoiceDataList": [],
      "ColorTextInfoList": []
    },
    {
      "Name": "千明代表",
      "Text": "啊哈哈。那份心意我就收下囉。抱歉，我必須要先走了。",
      "ChoiceDataList": [],
      "ColorTextInfoList": []
    },
    {
      "Name": "看似緊張的馬娘",
      "Text": "啊，千明學姊！",
      "ChoiceDataList": [],
      "ColorTextInfoList": []
    },
    {
      "Name": "獨白",
      "Text": "聚集在此的人們大家都追著千明代表離開了。再來──",
      "ChoiceDataList": [],
      "ColorTextInfoList": []
    },
    {
      "Name": "葛城王牌",
      "Text": "哈啊、哈啊……咳、哈……哈啊……。",
      "ChoiceDataList": [],
      "ColorTextInfoList": []
    },
    {
      "Name": "獨白",
      "Text": "仍上氣不接下氣地邊大口喘氣，邊站在那裡的是──",
      "ChoiceDataList": [
        "（她是叫……葛城王牌嗎？）"
      ],
      "ColorTextInfoList": []
    },
    {
      "Name": "葛城王牌",
      "Text": "可惡……哈、哈啊……。果然、還是輸了……可惡……！",
      "ChoiceDataList": [],
      "ColorTextInfoList": []
    },
    {
      "Name": "葛城王牌",
      "Text": "哈啊……面對千明，要從那個位置逃開……\n實在是……哈、哈啊……哈啊……。",
      "ChoiceDataList": [],
      "ColorTextInfoList": []
    },
    {
      "Name": "獨白",
      "Text": "跑那麼久之後還能完成這場併跑已經讓我深感佩服了。\n即便如此，輸了肯定還是會覺得不甘心吧。",
      "ChoiceDataList": [
        "（該說跑得很好之類的……還是）"
      ],
      "ColorTextInfoList": []
    },
    {
      "Name": "獨白",
      "Text": "還是該更直接地誇獎她說「下次再努力吧」？\n雖然不是擔當馬娘，但我無法放著沮喪的馬娘不管──",
      "ChoiceDataList": [],
      "ColorTextInfoList": []
    },
    {
      "Name": "葛城王牌",
      "Text": "哈……大家竟然都背對我……。",
      "ChoiceDataList": [],
      "ColorTextInfoList": []
    },
    {
      "Name": "葛城王牌",
      "Text": "果然是被瞧不起了。不，甚至不存在於視界中嗎？\n……也對，那是當然的。",
      "ChoiceDataList": [],
      "ColorTextInfoList": []
    },
    {
      "Name": "葛城王牌",
      "Text": "──哈哈！我絕對要贏給你們看……！！\n等著看吧，能站在那邊笑的也只有現在了！",
      "ChoiceDataList": [],
      "ColorTextInfoList": []
    },
    {
      "Name": "葛城王牌",
      "Text": "總有一天……我一定會讓你們追逐我的背影……！",
      "ChoiceDataList": [],
      "ColorTextInfoList": []
    }
  ]
}