{
  "Title": "仔細檢查！",
  "TextBlockList": [
    {
      "Name": "",
      "Text": "",
      "ChoiceDataList": [],
      "ColorTextInfoList": []
    },
    {
      "Name": "獨白",
      "Text": "放學後，我到處散步，轉換心情……",
      "ChoiceDataList": [],
      "ColorTextInfoList": []
    },
    {
      "Name": "成田路",
      "Text": "──好！燈光跟音效都很正常。\n再來就只剩下檢查觀眾席……",
      "ChoiceDataList": [
        "妳在檢查舞台嗎……？"
      ],
      "ColorTextInfoList": []
    },
    {
      "Name": "成田路",
      "Text": "啊，對！\n因為明天我們班有演唱會的實習課。",
      "ChoiceDataList": [],
      "ColorTextInfoList": []
    },
    {
      "Name": "成田路",
      "Text": "所以我想要來這邊巡一下，\n讓大家明天都能開開心心地學習！",
      "ChoiceDataList": [
        "原來如此，真了不起呢",
        "原來如此，真了不起呢"
      ],
      "ColorTextInfoList": []
    },
    {
      "Name": "成田路",
      "Text": "哈哈！謝謝你的誇獎！\n不過，\n像這樣的事情也是班長的責任吧。",
      "ChoiceDataList": [],
      "ColorTextInfoList": []
    },
    {
      "Name": "成田路",
      "Text": "所以這也不是什麼值得誇獎的事情──",
      "ChoiceDataList": [],
      "ColorTextInfoList": []
    },
    {
      "Name": "成田路",
      "Text": "……嗯？剛剛好像被水滴到了？\n是下雨了嗎……？",
      "ChoiceDataList": [
        "要不要乾脆先休息？",
        "趕快檢查完吧！"
      ],
      "ColorTextInfoList": []
    },
    {
      "Name": "成田路",
      "Text": "也對，我們去校舍躲雨吧。\n要快點才行……！",
      "ChoiceDataList": [],
      "ColorTextInfoList": []
    },
    {
      "Name": "成田路",
      "Text": "──呼……！\n還好我們都沒淋濕。",
      "ChoiceDataList": [],
      "ColorTextInfoList": []
    },
    {
      "Name": "成田路",
      "Text": "看來好像只是陣雨……\n應該很快就會停了，太好了。",
      "ChoiceDataList": [],
      "ColorTextInfoList": []
    },
    {
      "Name": "成田路",
      "Text": "對了……\n我乾脆趁現在去幫教室的花瓶換水吧。",
      "ChoiceDataList": [],
      "ColorTextInfoList": []
    },
    {
      "Name": "成田路",
      "Text": "還要補粉筆……\n還要用板擦機清理板擦！",
      "ChoiceDataList": [
        "妳不用休息嗎？",
        "妳不用休息嗎？"
      ],
      "ColorTextInfoList": []
    },
    {
      "Name": "成田路",
      "Text": "呵呵！這就是順便休息啊。\n這種單調的事情可以幫助人放鬆身心。",
      "ChoiceDataList": [],
      "ColorTextInfoList": []
    },
    {
      "Name": "成田路",
      "Text": "那麼，我就先告辭了！",
      "ChoiceDataList": [],
      "ColorTextInfoList": []
    },
    {
      "Name": "獨白",
      "Text": "隔天，我通過舞台旁邊的時候，\n成田路說的實習課似乎剛好正在進行……",
      "ChoiceDataList": [],
      "ColorTextInfoList": []
    },
    {
      "Name": "成田路",
      "Text": "嗯！我會在雨勢變大之前處理完！",
      "ChoiceDataList": [],
      "ColorTextInfoList": []
    },
    {
      "Name": "成田路",
      "Text": "訓練員也趕快去躲雨，\n以免被淋濕喔！",
      "ChoiceDataList": [
        "啊，我也來幫忙……",
        "啊，我也來幫忙……"
      ],
      "ColorTextInfoList": []
    },
    {
      "Name": "獨白",
      "Text": "成田路以驚人的速度跑過觀眾席之間，\n用眼睛檢視座位。",
      "ChoiceDataList": [],
      "ColorTextInfoList": []
    },
    {
      "Name": "成田路",
      "Text": "──啊！椅子底下有空罐！\n大概是放在這裡就忘記帶走了……！",
      "ChoiceDataList": [
        "（看來也不需要我幫忙呢）"
      ],
      "ColorTextInfoList": []
    },
    {
      "Name": "獨白",
      "Text": "她似乎本來做事就很有效率，\n一下子就檢查完所有座位，然後朝校舍跑去。",
      "ChoiceDataList": [],
      "ColorTextInfoList": []
    },
    {
      "Name": "獨白",
      "Text": "隔天，我通過舞台旁邊的時候，\n成田路說的實習課似乎剛好正在進行……",
      "ChoiceDataList": [],
      "ColorTextInfoList": []
    },
    {
      "Name": "賽馬娘A",
      "Text": "咦？場地上的記號本來有這麼清楚嗎？\n而且地板是不是也變乾淨了？",
      "ChoiceDataList": [],
      "ColorTextInfoList": []
    },
    {
      "Name": "賽馬娘B",
      "Text": "對啊～！狀態不太好的麥克風也被換掉了！\n……該不會是班長先弄好的……？",
      "ChoiceDataList": [],
      "ColorTextInfoList": []
    },
    {
      "Name": "成田路",
      "Text": "大家！我們要開始實習了喔！\n先別聊天了，該整隊了喔～！",
      "ChoiceDataList": [],
      "ColorTextInfoList": []
    },
    {
      "Name": "獨白",
      "Text": "學生們喊著「好～！」並乖乖排好隊。\n看來成田路是個做事俐落，\n還會在背後默默支持大家的人……！",
      "ChoiceDataList": [],
      "ColorTextInfoList": []
    }
  ]
}