{
  "Title": "Breakdown.",
  "TextBlockList": [
    {
      "Name": "",
      "Text": "",
      "ChoiceDataList": [],
      "ColorTextInfoList": []
    },
    {
      "Name": "フジキセキ",
      "Text": "さて、どうやら君も本腰を入れてくれるようだし……\n構成は一旦置いて、基本的なステップのおさらいをしようか。",
      "ChoiceDataList": [],
      "ColorTextInfoList": []
    },
    {
      "Name": "フジキセキ",
      "Text": "――それっ！\u3000ふふっ……♪\nうん！\u3000さっきより噛み合ってきたね！",
      "ChoiceDataList": [],
      "ColorTextInfoList": []
    },
    {
      "Name": "セイウンスカイ",
      "Text": "（……っ。\nそんな顔、するんだ――）",
      "ChoiceDataList": [],
      "ColorTextInfoList": []
    },
    {
      "Name": "フジキセキ",
      "Text": "ふふっ……上手いじゃないか！\nより気持ちが入ったから、かな？",
      "ChoiceDataList": [],
      "ColorTextInfoList": []
    },
    {
      "Name": "セイウンスカイ",
      "Text": "……フジさんこそ、\nさっきよりノリノリだったじゃないですか。",
      "ChoiceDataList": [],
      "ColorTextInfoList": []
    },
    {
      "Name": "フジキセキ",
      "Text": "君の仲間たちが盛り上がってくれるのが嬉しくてね。\nデビューしていると、この時期は忙しいだろう？",
      "ChoiceDataList": [],
      "ColorTextInfoList": []
    },
    {
      "Name": "セイウンスカイ",
      "Text": "まあ、大きなレースもいろいろ始まりますから。\r\n……2度はないシーズンを迎える子もいますし。",
      "ChoiceDataList": [],
      "ColorTextInfoList": []
    },
    {
      "Name": "フジキセキ",
      "Text": "だから必然的に、ドロワの主役は……このタイミングで、\n『全てをやり切った子たち』になる。",
      "ChoiceDataList": [],
      "ColorTextInfoList": []
    },
    {
      "Name": "セイウンスカイ",
      "Text": "……。",
      "ChoiceDataList": [],
      "ColorTextInfoList": []
    },
    {
      "Name": "フジキセキ",
      "Text": "今までのドロワは、思い出づくりの側面が強かったと思う。\n次のステップに進むために、とても大切なことだよね。",
      "ChoiceDataList": [],
      "ColorTextInfoList": []
    },
    {
      "Name": "フジキセキ",
      "Text": "だからこそ、私が思うに……ドロワは、『気持ちを新たにする』、\n全ての子のための儀式であってほしいんだ。",
      "ChoiceDataList": [],
      "ColorTextInfoList": []
    },
    {
      "Name": "フジキセキ",
      "Text": "まだデビューしていない子も、すでにした子も……\r\n日々色んな想いを抱えて、夢や目標に向かって努力している。",
      "ChoiceDataList": [],
      "ColorTextInfoList": []
    },
    {
      "Name": "フジキセキ",
      "Text": "けれど誰も――どれほど強い子でも、休憩なしで走り続けられない。\n息をつくタイミング……今日を明日に切り替える区切りがなくちゃ。",
      "ChoiceDataList": [],
      "ColorTextInfoList": []
    },
    {
      "Name": "フジキセキ",
      "Text": "だから、できるだけたくさんの子に参加してほしいんだよ。\n特に、目標を果たすまで、ずっと走り続けられちゃう子にはね。",
      "ChoiceDataList": [],
      "ColorTextInfoList": []
    },
    {
      "Name": "フジキセキ",
      "Text": "みんなが、楽しい気持ちでまた1年頑張れるように……\n私にできることは全てしたいんだ。",
      "ChoiceDataList": [],
      "ColorTextInfoList": []
    },
    {
      "Name": "セイウンスカイ",
      "Text": "（……なるほどねぇ。\nフジさんの目的、ようやく理解できた）",
      "ChoiceDataList": [],
      "ColorTextInfoList": []
    },
    {
      "Name": "セイウンスカイ",
      "Text": "（この人……本当にただ、ドロワを盛り上げたいだけなんだ。\nなら……）",
      "ChoiceDataList": [],
      "ColorTextInfoList": []
    },
    {
      "Name": "セイウンスカイ",
      "Text": "……私、やっぱりフジさんの相手にふさわしくないですよ。\r\n嫌だからじゃなくて、単純に私とフジさんって全然違うんです。",
      "ChoiceDataList": [],
      "ColorTextInfoList": []
    },
    {
      "Name": "セイウンスカイ",
      "Text": "勘違いしてるみたいですけど、私は自分のことしか興味なくて。\n『みんなに笑顔を☆』……みたいな作戦は、考えたこともない。",
      "ChoiceDataList": [],
      "ColorTextInfoList": []
    },
    {
      "Name": "フジキセキ",
      "Text": "勘違いじゃないと思うよ。\nだって、私が『君がいい』と思ったのは……。",
      "ChoiceDataList": [],
      "ColorTextInfoList": []
    },
    {
      "Name": "フジキセキ",
      "Text": "…………。",
      "ChoiceDataList": [],
      "ColorTextInfoList": []
    },
    {
      "Name": "フジキセキ",
      "Text": "……とにかく、君となら、みんなをもっともっと！\n笑顔にできると思ったんだよ。",
      "ChoiceDataList": [],
      "ColorTextInfoList": []
    },
    {
      "Name": "セイウンスカイ",
      "Text": "……。",
      "ChoiceDataList": [],
      "ColorTextInfoList": []
    },
    {
      "Name": "モノローグ",
      "Text": "（～♪）",
      "ChoiceDataList": [],
      "ColorTextInfoList": []
    },
    {
      "Name": "エアシャカール",
      "Text": "――ア゛ー……。",
      "ChoiceDataList": [],
      "ColorTextInfoList": []
    },
    {
      "Name": "エアシャカール",
      "Text": "……ノリはパーティーっぽいが、ノイズにしかなンねェな。\nやっぱ踊らせりゃいいってのは好かねェ……っつか。",
      "ChoiceDataList": [],
      "ColorTextInfoList": []
    },
    {
      "Name": "エアシャカール",
      "Text": "（なにやってンだオレは……プレイリスト組んでみたりして。\nどれもこれも、あの会長サマがわけわかんねェことすンのが悪い）",
      "ChoiceDataList": [],
      "ColorTextInfoList": []
    },
    {
      "Name": "エアシャカール",
      "Text": "（――『!monad』宛にDJ依頼なンか！\nなンッでオレの別名義を知ってンだよ！？）",
      "ChoiceDataList": [],
      "ColorTextInfoList": []
    },
    {
      "Name": "エアシャカール",
      "Text": "（オレはひっそりやってたンだよ。分析のガス抜き程度に、\n手慰みで打ち込みしてた。完全にド素人の遊びだ）",
      "ChoiceDataList": [],
      "ColorTextInfoList": []
    },
    {
      "Name": "エアシャカール",
      "Text": "（……まァ、それなりのモンができたら売ったりもしてたが。\n投稿したモノがバズッたこともねェ。なのに――）",
      "ChoiceDataList": [],
      "ColorTextInfoList": []
    },
    {
      "Name": "エアシャカール",
      "Text": "（どこから嗅ぎつけてきやがった！？\u3000わかってて引きずりだそう\nとしてンなら、相当タチ悪ィ……いや、偶然のほうが最悪か）",
      "ChoiceDataList": [],
      "ColorTextInfoList": []
    },
    {
      "Name": "エアシャカール",
      "Text": "（マジでなに考えてる？\u3000急にDJタイムとか思いつくか？\r\nつかそもそも、DJなンか人前でやったことねェし。まあ……）",
      "ChoiceDataList": [],
      "ColorTextInfoList": []
    },
    {
      "Name": "エアシャカール",
      "Text": "――っと！？\u3000マジか……。",
      "ChoiceDataList": [],
      "ColorTextInfoList": []
    },
    {
      "Name": "シンボリルドルフ",
      "Text": "……――",
      "ChoiceDataList": [],
      "ColorTextInfoList": []
    },
    {
      "Name": "シリウスシンボリ",
      "Text": "『祝福』？\u3000『前へと踏み出せる区切り』？\r\nお前が、それを、与えたいだけ……これがエゴでなくてなんなんだ？",
      "ChoiceDataList": [],
      "ColorTextInfoList": []
    },
    {
      "Name": "シンボリルドルフ",
      "Text": "（……つい、傲岸不遜な態度をとってしまった。\nシリウスに非はない。この時期……私は少し、弱くなる）",
      "ChoiceDataList": [],
      "ColorTextInfoList": []
    },
    {
      "Name": "シンボリルドルフ",
      "Text": "（学園生活を全うし走り去る子たち。\nその笑顔に重なる――いや、重ねてしまう涙……）",
      "ChoiceDataList": [],
      "ColorTextInfoList": []
    },
    {
      "Name": "シンボリルドルフ",
      "Text": "（やはり、全ては私のエゴなのだろうか？\nそのような放辟邪侈な理由で、皆を祝福など……）",
      "ChoiceDataList": [],
      "ColorTextInfoList": []
    },
    {
      "Name": "フジキセキ",
      "Text": "浮かない顔ですね、会長？",
      "ChoiceDataList": [],
      "ColorTextInfoList": []
    },
    {
      "Name": "シンボリルドルフ",
      "Text": "フジキセキ。珍しいね、こんなところで。いや、それよりも……\nとても美しいよ。解語之花とは、君を指す言葉だな。",
      "ChoiceDataList": [],
      "ColorTextInfoList": []
    },
    {
      "Name": "フジキセキ",
      "Text": "ふふ、言いすぎです。それに……物思いに耽る貴方の横顔のほうが、\n心を惹かれてしまう……私でよければ、お力になれませんか？",
      "ChoiceDataList": [],
      "ColorTextInfoList": []
    },
    {
      "Name": "シンボリルドルフ",
      "Text": "いや、エキシビションダンスに、生徒たちへの指導……\n君はもう、大いに力になってくれているよ。",
      "ChoiceDataList": [],
      "ColorTextInfoList": []
    },
    {
      "Name": "フジキセキ",
      "Text": "なるほど、ドロワのことでしたか。とはいえ、気にされていた\n参加率は、例年より増えそうだと私は感じていますが……？",
      "ChoiceDataList": [],
      "ColorTextInfoList": []
    },
    {
      "Name": "フジキセキ",
      "Text": "もしかして、DJタイム導入のほうで滞りでも？\n投書アプリに意見があった、まではお聞きしましたが……。",
      "ChoiceDataList": [],
      "ColorTextInfoList": []
    },
    {
      "Name": "フジキセキ",
      "Text": "確か……『ドレスやダンスには相応しくないけど、\n大好きな仲間たちと“思い出”を残すきっかけがほしい』……とか。",
      "ChoiceDataList": [],
      "ColorTextInfoList": []
    },
    {
      "Name": "シンボリルドルフ",
      "Text": "ああ。きっと、他にも同じ想いの子がいる。\r\n彼女たちが足を向けられる、きっかけになればと採用した。",
      "ChoiceDataList": [],
      "ColorTextInfoList": []
    },
    {
      "Name": "シンボリルドルフ",
      "Text": "ただ、投書に名前のあった作曲家に声をかけているが、\n返事はなし……並行で生徒の中からもDJを募っているところだな。",
      "ChoiceDataList": [],
      "ColorTextInfoList": []
    },
    {
      "Name": "フジキセキ",
      "Text": "なるほど。とはいえ、進行に問題はないわけですよね。\nであれば……会長ご自身に、迷いがある……？",
      "ChoiceDataList": [],
      "ColorTextInfoList": []
    },
    {
      "Name": "シンボリルドルフ",
      "Text": "……それ以上は、君らしくないようにも思えるよ。\nここまで追いかけてきた時点で、だけれど。",
      "ChoiceDataList": [],
      "ColorTextInfoList": []
    },
    {
      "Name": "フジキセキ",
      "Text": "ありゃ。……ですが踏み込むべきと、そうでない時の\n判断はつけられるつもりです。……聞かせてくれませんか？",
      "ChoiceDataList": [],
      "ColorTextInfoList": []
    }
  ]
}